cookware/__init__.py
cookware/__version__.py
cookware-0.0.1.dist-info/LICENSE
cookware-0.0.1.dist-info/METADATA
cookware-0.0.1.dist-info/WHEEL
cookware-0.0.1.dist-info/top_level.txt
cookware-0.0.1.dist-info/RECORD
